{
  "display": {
    "icon": {
      "item": "redstoneutilz:copycat_button"
    },
    "title": {
      "translate": "advancements.redstoneutilz.configurable_copycat_button_get.title"
    },
    "description": {
      "translate": "advancements.redstoneutilz.configurable_copycat_button_get.descr"
    },
    "frame": "challenge",
    "show_toast": true,
    "announce_to_chat": true,
    "hidden": false
  },
  "criteria": {
    "requirement": {
      "trigger": "minecraft:inventory_changed",
      "conditions": {
        "player": {},
        "items": [
          {
            "items": [
              "redstoneutilz:copycat_button"
            ],
            "count": {
              "min": 1,
              "max": 999
            }
          }
        ]
      }
    }
  },
  "parent": "redstoneutilz:copycat_block_get"
}
