{
  "display": {
    "background": "redstoneutilz:textures/block/zinc_block.png",
    "icon": {
      "item": "redstoneutilz:zinc_ingot"
    },
    "title": {
      "translate": "advancements.redstoneutilz.zinc_ingot_get.title"
    },
    "description": {
      "translate": "advancements.redstoneutilz.zinc_ingot_get.descr"
    },
    "frame": "challenge",
    "show_toast": true,
    "announce_to_chat": true,
    "hidden": false
  },
  "criteria": {
    "requirement": {
      "trigger": "minecraft:inventory_changed",
      "conditions": {
        "player": {},
        "items": [
          {
            "items": [
              "redstoneutilz:zinc_ingot"
            ],
            "count": {
              "min": 1,
              "max": 999
            }
          }
        ]
      }
    }
  }
}
